shinobi_client/__init__.py
shinobi_client/_common.py
shinobi_client/api_key.py
shinobi_client/cli.py
shinobi_client/client.py
shinobi_client/orms/__init__.py
shinobi_client/orms/monitor.py
shinobi_client/orms/user.py
shinobi_client/shinobi_controller.py
shinobi_client/tests/__init__.py
shinobi_client/tests/_common.py
shinobi_client/tests/orms/__init__.py
shinobi_client/tests/orms/test_monitor.py
shinobi_client/tests/orms/test_user.py
shinobi_client/tests/resources/__init__.py
shinobi_client/tests/resources/metadata.py
shinobi_client/tests/resources/monitors/details-as-json.json
shinobi_client/tests/resources/monitors/example-1.json
shinobi_client/tests/resources/monitors/example-2.json
shinobi_client/tests/test_api_key.py
shinobi_client/tests/test_client.py
shinobi_client/tests/test_shinobi_controller.py
shinobi_client-3.1.1.dist-info/LICENSE.txt
shinobi_client-3.1.1.dist-info/WHEEL
shinobi_client-3.1.1.dist-info/METADATA
shinobi_client-3.1.1.dist-info/RECORD
