Metadata-Version: 2.1
Name: shinobi-client
Version: 3.1.1
Summary: A Python client for controlling Shinobi (an open-source video management solution)
Home-page: https://github.com/colin-nolan/python-shinobi-client
License: GPL v3.0
Keywords: shinobi,client,cli
Author: Colin Nolan
Author-email: cn580@alumni.york.ac.uk
Requires-Python: >=3.6,<4.0
Classifier: License :: Other/Proprietary License
Classifier: Programming Language :: Python :: 3
Classifier: Programming Language :: Python :: 3.6
Classifier: Programming Language :: Python :: 3.7
Classifier: Programming Language :: Python :: 3.8
Classifier: Programming Language :: Python :: 3.9
Provides-Extra: cli
Provides-Extra: shinobi-controller
Requires-Dist: dataclasses (>=0.7,<0.8); python_version >= "3.6" and python_version < "3.7"
Requires-Dist: docker (>=4,<5); extra == "shinobi-controller"
Requires-Dist: docker-compose (>=1.25,<2.0); extra == "shinobi-controller"
Requires-Dist: fire (>=0.3.0,<0.4.0); extra == "cli"
Requires-Dist: get-port (>=0.0.5,<0.0.6); extra == "shinobi-controller"
Requires-Dist: gitpython (>=3,<4); extra == "shinobi-controller"
Requires-Dist: logzero (>=1.5.0,<2.0.0)
Requires-Dist: requests (>=2.23,<3.0)
Requires-Dist: toml (>=0.9,<0.10)
Project-URL: Repository, https://github.com/colin-nolan/python-shinobi-client
